opensea/__init__.py
opensea/assets.py
opensea/bundles.py
opensea/collection_stats.py
opensea/common.py
opensea/models/__init__.py
opensea/models/account.py
opensea/models/asset.py
opensea/models/bundle.py
opensea/models/collection_stats.py
opensea-0.2.0.dist-info/METADATA
opensea-0.2.0.dist-info/WHEEL
opensea-0.2.0.dist-info/top_level.txt
opensea-0.2.0.dist-info/RECORD
