Metadata-Version: 2.1
Name: opensea
Version: 0.2.0
Summary: wrapper library for opensea api
Home-page: UNKNOWN
Author: Ankush Singh
Author-email: ankush4singh@gmail.com
License: MIT
Platform: UNKNOWN
Classifier: Intended Audience :: Developers
Classifier: License :: OSI Approved :: MIT License
Classifier: Programming Language :: Python :: 3
Classifier: Operating System :: OS Independent
Requires-Dist: requests
